__init__.py
eve_smlm/DeveloperInstructions.md
eve_smlm/Eve.png
eve_smlm/GUI.py
eve_smlm/GUI_main.py
eve_smlm/README.md
eve_smlm/ScientificBackground.md
eve_smlm/CandidateFinding/DBSCAN.py
eve_smlm/CandidateFinding/EigenFeatureAnalysis.py
eve_smlm/CandidateFinding/FrameBasedFinding.py
eve_smlm/CandidateFinding/LoadExistingFinding.py
eve_smlm/CandidateFinding/__init__.py
eve_smlm/CandidateFitting/GaussianFitting.py
eve_smlm/CandidateFitting/LoadExistingFitting.py
eve_smlm/CandidateFitting/PhasorFitting.py
eve_smlm/CandidateFitting/Radial_Symmetry.py
eve_smlm/CandidateFitting/SimpleOperants.py
eve_smlm/CandidateFitting/__init__.py
eve_smlm/CandidatePreview/CumulativeSum.py
eve_smlm/CandidatePreview/OneDProjection.py
eve_smlm/CandidatePreview/ThreeDPointClouds.py
eve_smlm/CandidatePreview/TwoDFirstEvents.py
eve_smlm/CandidatePreview/TwoDProjections.py
eve_smlm/CandidatePreview/TwoDTimedelays.py
eve_smlm/CandidatePreview/TwoDTimestamps.py
eve_smlm/CandidatePreview/__init__.py
eve_smlm/EventDistributions/eventDistributions.py
eve_smlm/Markdown_info/Exported Items.bib
eve_smlm/Markdown_info/Fig_DevManual.png
eve_smlm/Markdown_info/SciBG_2dGaussTime.png
eve_smlm/Markdown_info/SciBG_AllFirstEvents.png
eve_smlm/Markdown_info/SciBG_DBSCAN.png
eve_smlm/Markdown_info/SciBG_EigenFeature.png
eve_smlm/Markdown_info/SciBG_LogNorm.png
eve_smlm/Markdown_info/SciBG_cluster.png
eve_smlm/Markdown_info/SciBG_lifetime.png
eve_smlm/Markdown_info/citations.bib
eve_smlm/Markdown_info/finalSIHeader.md
eve_smlm/Markdown_info/header.tex
eve_smlm/Markdown_info/ieee.csl
eve_smlm/Markdown_info/styles.css
eve_smlm/PostProcessing/DriftCorr_DME.py
eve_smlm/PostProcessing/Filter.py
eve_smlm/PostProcessing/Histogramming.py
eve_smlm/PostProcessing/PolarityMatching.py
eve_smlm/PostProcessing/ResolutionDetermination.py
eve_smlm/PostProcessing/__init__.py
eve_smlm/PostProcessing/dme/dme_example.py
eve_smlm/PostProcessing/dme/bin/release/api-ms-win-crt-heap-l1-1-0.dll
eve_SMLM-0.2.1.dist-info/LICENCE
eve_SMLM-0.2.1.dist-info/METADATA
eve_SMLM-0.2.1.dist-info/WHEEL
eve_SMLM-0.2.1.dist-info/entry_points.txt
eve_SMLM-0.2.1.dist-info/top_level.txt
eve_SMLM-0.2.1.dist-info/RECORD
